cssbeautifier/__init__.py
cssbeautifier/__version__.py
cssbeautifier/beautifier.py
cssbeautifier/directives.py
cssbeautifier/inputscanner.py
cssbeautifier/options.py
cssbeautifier/output.py
css_beautify-1.10.3.dist-info/LICENSE
css_beautify-1.10.3.dist-info/METADATA
css_beautify-1.10.3.dist-info/WHEEL
css_beautify-1.10.3.dist-info/entry_points.txt
css_beautify-1.10.3.dist-info/top_level.txt
css_beautify-1.10.3.dist-info/RECORD
